kotorcli/__init__.py
kotorcli/__main__.py
kotorcli/app.py
kotorcli/cfg_parser.py
kotorcli/config.py
kotorcli/gui_converter.py
kotorcli/indoor_builder.py
kotorcli/kit_generator.py
kotorcli/logger.py
kotorcli/commands/__init__.py
kotorcli/commands/cat.py
kotorcli/commands/compile.py
kotorcli/commands/config.py
kotorcli/commands/convert.py
kotorcli/commands/create_archive.py
kotorcli/commands/diff_installation.py
kotorcli/commands/extract.py
kotorcli/commands/format_convert.py
kotorcli/commands/gui_convert.py
kotorcli/commands/indoor_builder.py
kotorcli/commands/init.py
kotorcli/commands/install.py
kotorcli/commands/key_pack.py
kotorcli/commands/kit_generate.py
kotorcli/commands/launch.py
kotorcli/commands/list.py
kotorcli/commands/list_archive.py
kotorcli/commands/pack.py
kotorcli/commands/patching.py
kotorcli/commands/resource_tools.py
kotorcli/commands/script_tools.py
kotorcli/commands/search_archive.py
kotorcli/commands/unpack.py
kotorcli/commands/utility_commands.py
kotorcli/commands/validation.py
kotorcli/diff_tool/__init__.py
kotorcli/diff_tool/__main__.py
kotorcli/diff_tool/app.py
kotorcli/diff_tool/cli.py
kotorcli/diff_tool/cli_utils.py
kotorcli/diff_tool/differ.py
kotorcli/diff_tool/formatters.py
kotorcli/diff_tool/gui.py
kotorcli/diff_tool/logger.py
kotorcli-1.2.1.dist-info/METADATA
kotorcli-1.2.1.dist-info/WHEEL
kotorcli-1.2.1.dist-info/entry_points.txt
kotorcli-1.2.1.dist-info/top_level.txt
kotorcli-1.2.1.dist-info/RECORD
